mwdb_plugin_drakvuf/__init__.py
mwdb_plugin_drakvuf/config.py
mwdb_plugin_drakvuf/plugin.py
mwdb_plugin_drakvuf-0.1.0.dist-info/LICENSE
mwdb_plugin_drakvuf-0.1.0.dist-info/METADATA
mwdb_plugin_drakvuf-0.1.0.dist-info/WHEEL
mwdb_plugin_drakvuf-0.1.0.dist-info/top_level.txt
mwdb_plugin_drakvuf-0.1.0.dist-info/RECORD
